fitparserx/__init__.py
fitparserx/parser.py
fitparserx-0.1.5.dist-info/licenses/LICENSE.md
fitparserx-0.1.5.dist-info/METADATA
fitparserx-0.1.5.dist-info/WHEEL
fitparserx-0.1.5.dist-info/top_level.txt
fitparserx-0.1.5.dist-info/RECORD
