Metadata-Version: 2.4
Name: fitparserx
Version: 0.1.5
Summary: Parse Garmin .fit wellness data, process it, and make DataFrame and NumPy arrays
Author-email: Luka Antonic <lukaantonicx@gmail.com>
License: MIT License
Classifier: Programming Language :: Python :: 3
Classifier: License :: OSI Approved :: MIT License
Classifier: Operating System :: OS Independent
License-File: LICENSE.md
Requires-Dist: garmin_fit_sdk
Requires-Dist: numpy
Requires-Dist: pandas
Requires-Dist: pytz
Dynamic: license-file
